{
	"format_version": "1.12.0",
	"minecraft:geometry": [
		{
			"description": {
				"identifier": "geometry.pink_dolphin_v2",
				"texture_width": 128,
				"texture_height": 128,
				"visible_bounds_width": 8,
				"visible_bounds_height": 2.5,
				"visible_bounds_offset": [0, 0.75, 0]
			},
			"bones": [
				{
					"name": "dolphin",
					"pivot": [0, 0, 0],
					"cubes": [
						{"origin": [-6, 0, -16], "size": [12, 12, 24], "uv": [0, 0]}
					]
				},
				{
					"name": "cabeza",
					"parent": "dolphin",
					"pivot": [0, 6.5, -16],
					"cubes": [
						{"origin": [-6.5, 0, -28], "size": [13, 13, 12], "uv": [42, 51]}
					]
				},
				{
					"name": "boca0",
					"parent": "cabeza",
					"pivot": [0, 5.5, -28],
					"cubes": [
						{"origin": [-2.5, 4, -40], "size": [5, 3, 12], "uv": [38, 36]},
						{"origin": [-2.5, 4, -47.9], "size": [5, 3, 8], "inflate": -0.1, "uv": [69, 76]}
					]
				},
				{
					"name": "boca1",
					"parent": "cabeza",
					"pivot": [0, 4, -28],
					"cubes": [
						{"origin": [-2, 2, -39], "size": [4, 2, 11], "uv": [25, 76]},
						{"origin": [-2, 2.2, -47.5], "size": [4, 2, 9], "inflate": -0.1, "uv": [80, 0]}
					]
				},
				{
					"name": "tail0",
					"parent": "dolphin",
					"pivot": [0, 6, 9],
					"cubes": [
						{"origin": [-5.5, 0.5, 8], "size": [11, 11, 16], "uv": [0, 36]}
					]
				},
				{
					"name": "tail1",
					"parent": "tail0",
					"pivot": [0, 6, 25],
					"cubes": [
						{"origin": [-5, 1, 24], "size": [10, 10, 12], "uv": [48, 0]}
					]
				},
				{
					"name": "tail2",
					"parent": "tail1",
					"pivot": [0, 6, 37],
					"cubes": [
						{"origin": [-4, 2, 36], "size": [8, 8, 10], "uv": [62, 26]},
						{"origin": [-14, 2, 36], "size": [10, 1, 8], "pivot": [-4, 3, 36], "rotation": [0, 35, 0], "uv": [0, 72]},
						{"origin": [4, 2, 36], "size": [10, 1, 8], "pivot": [4, 3, 36], "rotation": [0, -35, 0], "uv": [0, 63]}
					]
				},
				{
					"name": "right_fin",
					"parent": "dolphin",
					"pivot": [6, 1, -1],
					"rotation": [0, -25, 20],
					"cubes": [
						{"origin": [6, 1, -2], "size": [12, 1, 6], "uv": [0, 89]}
					]
				},
				{
					"name": "left_fin",
					"parent": "dolphin",
					"pivot": [-6, 1, -1],
					"rotation": [0, 25, -20],
					"cubes": [
						{"origin": [-18, 1, -2], "size": [12, 1, 6], "uv": [80, 56]}
					]
				},
				{
					"name": "back_fin",
					"parent": "dolphin",
					"pivot": [0, 11, -6],
					"rotation": [-60, 0, 0],
					"cubes": [
						{"origin": [-0.5, 8.10192, -8.5], "size": [1, 13, 9], "inflate": -0.25, "pivot": [0, 5, -7], "rotation": [10, 0, 0], "uv": [0, 96]}
					]
				}
			]
		}
	]
}